{
  "feedback": [
    {
      "id": 1,
      "email": "test@gmail.com",
      "name": "test name",
      "phone": "1234567890"
    },
    {
      "id": 2,
      "email": "test2@gmail.com",
      "name": "testname2",
      "phone": "1434567890"
    },
    {
      "name": "dasdsddsa",
      "phone": "ww2323232",
      "email": "dsdasdasd@fdsfsd.ds",
      "id": 3
    },
    {
      "name": "dasdsddsa",
      "phone": "ww2323232",
      "email": "dsdasdasd@fdsfsd.ds",
      "id": 4
    },
    {
      "name": "dasdsddsa",
      "phone": "444444",
      "email": "dsdasdasd@fdsfsd.ds",
      "id": 5
    },
    {
      "name": "dasdsddsa",
      "phone": "342424234",
      "email": "dsdasdasd@fdsfsd.ds",
      "id": 6
    },
    {
      "name": "dasdsddsa",
      "phone": "+2323323232",
      "email": "dsdasdasd@fdsfsd.ds",
      "id": 7
    },
    {
      "name": "dasdsddsa",
      "phone": "2323323232",
      "email": "dsdasdasd@fdsfsd.ds",
      "id": 8
    },
    {
      "name": "dwqdwdqwdqwdqwdq",
      "phone": "777777777",
      "email": "qwdqwdqwd@dadwa.dwqdq",
      "id": 9
    },
    {
      "name": "dwqdwdqwdqwdqwdq",
      "phone": "777777777",
      "email": "qwdqwdqwd@dadwa.dwqdq",
      "id": 10
    },
    {
      "name": "dwqdwdqwdqwdqwdq",
      "phone": "777777777",
      "email": "qwdqwdqwd@dadwa.dwqdq",
      "id": 11
    },
    {
      "name": "wdwd",
      "phone": "2222222323",
      "email": "wdw@sd.ff",
      "id": 12
    },
    {
      "name": "fDFSFSDFSD",
      "phone": "222222233",
      "email": "dsfsd@fsd.d",
      "id": 13
    },
    {
      "name": "eeeeeeeeeeeeeeeee",
      "phone": "33333333333",
      "email": "fsdfsdf@FS.saddsa",
      "id": 14
    },
    {
      "name": "куцкуцкцукцк",
      "phone": "332423432432",
      "email": "dfsdfd@ffff.re",
      "id": 15
    },
    {
      "name": "fewewfewwefewfewfe",
      "phone": "123455678",
      "email": "fwefwe@ffefwfew.fds",
      "id": 16
    },
    {
      "name": "fewfwfwe",
      "phone": "2222222233",
      "email": "3rwerer@fse.df",
      "id": 17
    },
    {
      "name": "fewfwfwe",
      "phone": "2222222233",
      "email": "3rwerer@fse.df",
      "id": 18
    },
    {
      "name": "dsdsdsd efewew. fefewf.",
      "phone": "+2222222233",
      "email": "3rwerer@fse.df",
      "id": 19
    },
    {
      "name": "dsdsdsd efewew. fefewf.",
      "phone": "+2222222233",
      "email": "3rwedwrer@fse.df",
      "id": 20
    }
  ]
}